octoprint_swapxy/__init__.py
octoprint_swapxy/templates/swapxy_settings.jinja2
SwapXY-0.3.0.dist-info/LICENSE
SwapXY-0.3.0.dist-info/METADATA
SwapXY-0.3.0.dist-info/WHEEL
SwapXY-0.3.0.dist-info/entry_points.txt
SwapXY-0.3.0.dist-info/top_level.txt
SwapXY-0.3.0.dist-info/RECORD
