Metadata-Version: 2.1
Name: SwapXY
Version: 0.3.0
Summary: Swap and/or reverse the X and Y axes used by the jog controls
Home-page: https://gitlab.com/wolframmfg/octoprint-swapxy
Author: Andy Castille
Author-email: andy.castille@wolframmfg.com
License: GPLv3
Platform: UNKNOWN
Classifier: Development Status :: 5 - Production/Stable
Classifier: Environment :: Plugins
Classifier: Intended Audience :: End Users/Desktop
Classifier: Intended Audience :: Manufacturing
Classifier: Intended Audience :: Science/Research
Classifier: License :: OSI Approved :: GNU General Public License v3 (GPLv3)
Classifier: Natural Language :: English
Classifier: Operating System :: OS Independent
Classifier: Programming Language :: Python
Classifier: Topic :: Scientific/Engineering
Requires-Dist: OctoPrint
